maxentropy/__init__.py
max_entropy-0.0.1.dist-info/LICENSE
max_entropy-0.0.1.dist-info/METADATA
max_entropy-0.0.1.dist-info/WHEEL
max_entropy-0.0.1.dist-info/top_level.txt
max_entropy-0.0.1.dist-info/RECORD
