Metadata-Version: 2.1
Name: max-entropy
Version: 0.0.1
Summary: Scipy-style maximum entropy distributions
Home-page: https://dsbowen.gitlab.io/maxentropy
Author: Dillon Bowen
Author-email: dsbowen@wharton.upenn.edu
License: UNKNOWN
Platform: UNKNOWN
Classifier: Programming Language :: Python :: 3
Classifier: License :: OSI Approved :: MIT License
Classifier: Operating System :: OS Independent
Requires-Python: >=3.8
Requires-Dist: numpy
Requires-Dist: scipy
